digitalAssistAnt/__init__.py
digitalAssistAnt/keys.py
digitalAssistAnt/main.py
digitalAssistAnt/util.py
digitalAssistAnt-0.0.4.dist-info/LICENSE
digitalAssistAnt-0.0.4.dist-info/METADATA
digitalAssistAnt-0.0.4.dist-info/WHEEL
digitalAssistAnt-0.0.4.dist-info/top_level.txt
digitalAssistAnt-0.0.4.dist-info/RECORD
