Metadata-Version: 2.1
Name: digitalAssistAnt
Version: 0.0.4
Summary: Your Assist-ant
Author-email: Shubh <shubhbpl@gmail.com>
Project-URL: Homepage, https://github.com/shubhvjain/ant
Requires-Python: >=3.7
License-File: LICENSE
